{
    "1500-0094": {
        "estado": "ACTIVO",
        "fecha": "2024-10-17",
        "nombre": "GRUPO EL PLATEADO SA DE CV-ZIHUA",
        "direccion": "CARRETERA LAGOS DE MORENO UNION DE SAN ANTONIO #932-A",
        "telefono1": "(755) 554-4088",
        "telefono2": "(___) ___-____",
        "descripcion": "",
        "email": "",
        "referencia": "ENTRE CALLE CAMINO A LA LABOR Y CALLE ARROYO DE LA SAUCEDA",
        "obs": "TEL. (___) ___-____",
        "credito": true,
        "montoCredito": 50000.0,
        "diasCredito": 30,
        "interesCredito": "1.00",
        "saldo": 600.0,
        "nl": 0,
        "nc": "",
        "membresia": "2022-06-21",
        "nivel": 0,
        "modificado": "",
        "et1": "",
        "lineaDeCredito": ""
    },
    "1500-0095": {
        "estado": "ACTIVO",
        "fecha": "2024-11-01",
        "nombre": "AUTOS ACAPULCO SA DE CV-NISSAN ZIHUA",
        "direccion": "AV. COSTERA MIGUEL ALEMAN #706 MANZANA XII LOTE 1 COL. HORNOS CP 39357",
        "telefono1": "(755) 554-2400",
        "telefono2": "(755) 557-3383",
        "descripcion": "",
        "email": "",
        "referencia": "ENTRE CALLE FRANCISCO ULLOA Y DIEGO HURTADO DE MENDOZA",
        "obs": "",
        "credito": true,
        "montoCredito": 10000.0,
        "diasCredito": 7,
        "interesCredito": "1.00",
        "saldo": 1050.0,
        "nl": 0,
        "nc": "",
        "membresia": "2022-06-21",
        "nivel": 0,
        "modificado": "",
        "et1": "",
        "lineaDeCredito": ""
    },
    "1500-0114": {
        "estado": "ACTIVO",
        "fecha": "2024-10-14",
        "nombre": "ABRAHAM-URVAN",
        "direccion": "CONOCIDO, PETATLAN GRO.",
        "telefono1": "(755) 100-4719",
        "telefono2": "(755) 140-8222",
        "descripcion": "",
        "email": "",
        "referencia": "",
        "obs": "",
        "credito": true,
        "montoCredito": 5000.0,
        "diasCredito": 30,
        "interesCredito": "1.00",
        "saldo": 2100.0,
        "nl": 0,
        "nc": "",
        "membresia": "2022-06-26",
        "nivel": 0,
        "modificado": "",
        "et1": "",
        "lineaDeCredito": ""
    },
    "1500-0115": {
        "estado": "ACTIVO",
        "fecha": "2024-10-24",
        "nombre": "TELEFONIA POR CABLE SA DE CV-MEGACABLE",
        "direccion": "AV LAZARO CARDENAS #1694",
        "telefono1": "(___) ___-____",
        "telefono2": "(___) ___-____",
        "descripcion": "",
        "email": "",
        "referencia": "",
        "obs": "",
        "credito": true,
        "montoCredito": 20000.0,
        "diasCredito": 15,
        "interesCredito": "1.00",
        "saldo": 175.0,
        "nl": 0,
        "nc": "",
        "membresia": "2022-06-27",
        "nivel": 0,
        "modificado": "",
        "et1": "",
        "lineaDeCredito": ""
    },
    "1500-0117": {
        "estado": "ACTIVO",
        "fecha": "2024-10-23",
        "nombre": "OMAR ABSALON LACUNZA SOTELO-MATERIALES IXTAPA",
        "direccion": "AV. MARINA MAZATLAN #944 COL. RESIDENCIAL",
        "telefono1": "(755) 554-3827",
        "telefono2": "(755) 554-5001",
        "descripcion": "",
        "email": "",
        "referencia": "",
        "obs": "",
        "credito": true,
        "montoCredito": 10000.0,
        "diasCredito": 30,
        "interesCredito": "1.00",
        "saldo": 300.0,
        "nl": 0,
        "nc": "",
        "membresia": "2022-06-27",
        "nivel": 0,
        "modificado": "",
        "et1": "",
        "lineaDeCredito": ""
    },
    "1500-0119": {
        "estado": "ACTIVO",
        "fecha": "2024-10-29",
        "nombre": "LUIS ALBERTO RESENDIZ BASURTO-HERRERO",
        "direccion": "SANTA FLOR MZA 12 LT4 COL AMUZGOS CP 40894",
        "telefono1": "(755) 113-3638",
        "telefono2": "(___) ___-____",
        "descripcion": "",
        "email": "",
        "referencia": "",
        "obs": "",
        "credito": true,
        "montoCredito": 12000.0,
        "diasCredito": 30,
        "interesCredito": "1.00",
        "saldo": 700.0,
        "nl": 0,
        "nc": "",
        "membresia": "2022-06-27",
        "nivel": 0,
        "modificado": "",
        "et1": "",
        "lineaDeCredito": ""
    },
    "1500-0124": {
        "estado": "ACTIVO",
        "fecha": "2024-10-26",
        "nombre": "H. AYUNTAMIENTO",
        "direccion": "CONOCIDO ZIHUATANEJO",
        "telefono1": "(755) 111-0835",
        "telefono2": "(___) ___-____",
        "descripcion": "",
        "email": "",
        "referencia": "ALEXANDER",
        "obs": "",
        "credito": true,
        "montoCredito": 100000.0,
        "diasCredito": 30,
        "interesCredito": "1.00",
        "saldo": 31150.0,
        "nl": 0,
        "nc": "",
        "membresia": "2022-06-28",
        "nivel": 0,
        "modificado": "",
        "et1": "",
        "lineaDeCredito": ""
    },
    "1500-0130": {
        "estado": "ACTIVO",
        "fecha": "2024-09-23",
        "nombre": "BIMBO SA DE CV",
        "direccion": "COL. EL AEROPUERTO",
        "telefono1": "(443) 438-3329",
        "telefono2": "(___) ___-____",
        "descripcion": "",
        "email": "",
        "referencia": "CONTACTO: SR. ARMANDO GONZALEZ",
        "obs": "BUEN CLIENTE TEL. (755) 142-9964 TEL. (755) 115-6545",
        "credito": true,
        "montoCredito": 250000.0,
        "diasCredito": 30,
        "interesCredito": "1.00",
        "saldo": 57550.0,
        "nl": 0,
        "nc": "",
        "membresia": "2022-07-01",
        "nivel": 0,
        "modificado": "",
        "et1": "",
        "lineaDeCredito": ""
    },
    "1500-0134": {
        "estado": "ACTIVO",
        "fecha": "2024-10-11",
        "nombre": "JESUS ADRIAN ANTONIO RAMIREZ-239",
        "direccion": "MANZANA 10 LOTE 9 COL NUEVO MILENIUM CP 40880",
        "telefono1": "(755) 108-2334",
        "telefono2": "(___) ___-____",
        "descripcion": "",
        "email": "",
        "referencia": "",
        "obs": "",
        "credito": false,
        "montoCredito": 5000.0,
        "diasCredito": 30,
        "interesCredito": "1.00",
        "saldo": 1500.0,
        "nl": 0,
        "nc": "",
        "membresia": "2022-07-03",
        "nivel": 0,
        "modificado": "",
        "et1": "",
        "lineaDeCredito": ""
    },
    "1500-0139": {
        "estado": "ACTIVO",
        "fecha": "2024-10-14",
        "nombre": "PABLO ROMERO AMBARIO-AGUA DELFIN",
        "direccion": "MAR MUERTO 209 COL. ZONA INDUSTRIAL CP40880",
        "telefono1": "(755) 557-1251",
        "telefono2": "(755) 544-6187",
        "descripcion": "",
        "email": "",
        "referencia": "DON PABLO 7555544278",
        "obs": "TEL. (755) 554-4278",
        "credito": true,
        "montoCredito": 5000.0,
        "diasCredito": 30,
        "interesCredito": "0",
        "saldo": 4400.0,
        "nl": 0,
        "nc": "",
        "membresia": "2022-07-05",
        "nivel": 0,
        "modificado": "",
        "et1": "",
        "lineaDeCredito": "CLIENTE BASICO"
    },
    "1500-0103": {
        "estado": "ACTIVO",
        "fecha": "2024-10-08",
        "nombre": "EDUARDO ZUÑIGA RENTERIA",
        "direccion": "CALLE LOS MANGOS S/N LOC. LA SALITRERA CP 40886",
        "telefono1": "(332) 132-6844",
        "telefono2": "(___) ___-____",
        "descripcion": "",
        "email": "",
        "referencia": "",
        "obs": "",
        "credito": true,
        "montoCredito": 5000.0,
        "diasCredito": 30,
        "interesCredito": "1.00",
        "saldo": 1150.0,
        "nl": 0,
        "nc": "",
        "membresia": "2022-06-23",
        "nivel": 0,
        "modificado": "",
        "et1": "",
        "lineaDeCredito": ""
    },
    "1500-0112": {
        "estado": "ACTIVO",
        "fecha": "2024-10-23",
        "nombre": "JOAQUIN GONZALEZ RAMIREZ-AGUAQUIN",
        "direccion": "ZONA INDUSTRIAL",
        "telefono1": "(755) 554-3720",
        "telefono2": "(755) 554-2165",
        "descripcion": "",
        "email": "",
        "referencia": "",
        "obs": "",
        "credito": true,
        "montoCredito": 50000.0,
        "diasCredito": 30,
        "interesCredito": "1.00",
        "saldo": 1900.0,
        "nl": 0,
        "nc": "",
        "membresia": "2022-06-26",
        "nivel": 0,
        "modificado": "",
        "et1": "",
        "lineaDeCredito": ""
    },
    "1500-0133": {
        "estado": "ACTIVO",
        "fecha": "2024-10-21",
        "nombre": "MARIANO BARBA CORTEZ",
        "direccion": "COL. EL HUJAL CASA15",
        "telefono1": "(755) 100-0231",
        "telefono2": "(___) ___-____",
        "descripcion": "",
        "email": "",
        "referencia": "TAXI 350 UTAAZ",
        "obs": "",
        "credito": true,
        "montoCredito": 6000.0,
        "diasCredito": 30,
        "interesCredito": "1.00",
        "saldo": 2700.0,
        "nl": 0,
        "nc": "",
        "membresia": "2022-07-02",
        "nivel": 0,
        "modificado": "",
        "et1": "",
        "lineaDeCredito": ""
    },
    "1500-0145": {
        "estado": "ACTIVO",
        "fecha": "2024-10-26",
        "nombre": "ARMANDO COVARRUBIAS GOMEZ 141 ARRECIFE",
        "direccion": "VALLE ENCANTADO 14 COL. LA PUERTA",
        "telefono1": "(755) 130-6447",
        "telefono2": "(___) ___-____",
        "descripcion": "",
        "email": "",
        "referencia": "ARMANDO",
        "obs": "",
        "credito": true,
        "montoCredito": 30000.0,
        "diasCredito": 30,
        "interesCredito": "0",
        "saldo": 17550.0,
        "nl": 0,
        "nc": "",
        "membresia": "2022-07-07",
        "nivel": 0,
        "modificado": "",
        "et1": "",
        "lineaDeCredito": "EMPRESA BASICA"
    },
    "1500-0148": {
        "estado": "ACTIVO",
        "fecha": "2024-10-25",
        "nombre": "JAVIER VALDEOLIVAR IZAZAGA",
        "direccion": "C RIO BALSAS U HAB LA PUERTA DEL SOL 40880",
        "telefono1": "(755) 114-6015",
        "telefono2": "(___) ___-____",
        "descripcion": "",
        "email": "",
        "referencia": "TAXI 0620",
        "obs": "",
        "credito": true,
        "montoCredito": 3500.0,
        "diasCredito": 15,
        "interesCredito": "1.00",
        "saldo": 1800.0,
        "nl": 0,
        "nc": "",
        "membresia": "2022-07-08",
        "nivel": 0,
        "modificado": "",
        "et1": "",
        "lineaDeCredito": ""
    },
    "1500-0150": {
        "estado": "ACTIVO",
        "fecha": "2022-07-10",
        "nombre": "JORGE ALBERTO TORRES LOZANO",
        "direccion": "COL BENITO JUAREZ 40896 MZA 6 LT 13",
        "telefono1": "(332) 603-3890",
        "telefono2": "(___) ___-____",
        "descripcion": "",
        "email": "",
        "referencia": "",
        "obs": "",
        "credito": true,
        "montoCredito": 20000.0,
        "diasCredito": 30,
        "interesCredito": "1.00",
        "saldo": 1000.0,
        "nl": 0,
        "nc": "",
        "membresia": "2022-07-09",
        "nivel": 0,
        "modificado": "",
        "et1": "",
        "lineaDeCredito": ""
    },
    "1500-0153": {
        "estado": "ACTIVO",
        "fecha": "2024-10-08",
        "nombre": "JOSE GABRIEL SOTO RIVERA-AMIGO RUBEN",
        "direccion": "COL. AGUA DE CORREA ATRAS DE LA MARISQUERIA EL BRONCO CP40893",
        "telefono1": "(755) 138-5054",
        "telefono2": "(453) 107-3825",
        "descripcion": "",
        "email": "",
        "referencia": "TAXI 235 UTAAZ",
        "obs": "",
        "credito": true,
        "montoCredito": 5000.0,
        "diasCredito": 30,
        "interesCredito": "1.00",
        "saldo": 4400.0,
        "nl": 0,
        "nc": "",
        "membresia": "2022-07-11",
        "nivel": 0,
        "modificado": "",
        "et1": "",
        "lineaDeCredito": ""
    },
    "1500-0144": {
        "estado": "ACTIVO",
        "fecha": "2024-09-07",
        "nombre": "JOSE TRINIDAD HERNANDEZ BALBUENA",
        "direccion": "SIN NOMBRE PETATLAN GRO.",
        "telefono1": "(755) 100-0639",
        "telefono2": "(___) ___-____",
        "descripcion": "",
        "email": "",
        "referencia": "",
        "obs": "TEL. (755) 115-5821",
        "credito": true,
        "montoCredito": 30000.0,
        "diasCredito": 30,
        "interesCredito": "0",
        "saldo": 28200.0,
        "nl": 0,
        "nc": "",
        "membresia": "2022-07-06",
        "nivel": 0,
        "modificado": "",
        "et1": "",
        "lineaDeCredito": "EMPRESA BASICA"
    },
    "1500-0171": {
        "estado": "ACTIVO",
        "fecha": "2024-10-11",
        "nombre": "RUBEN RODRIGUEZ CHAVEZ-DISUDE",
        "direccion": "IGNACIO MANUEL ALTAMIRANO #24 COL. CENTRO",
        "telefono1": "(755) 554-6660",
        "telefono2": "(755) 554-3145",
        "descripcion": "",
        "email": "",
        "referencia": "",
        "obs": "",
        "credito": true,
        "montoCredito": 10000.0,
        "diasCredito": 30,
        "interesCredito": "1.00",
        "saldo": 70.0,
        "nl": 0,
        "nc": "",
        "membresia": "2022-07-21",
        "nivel": 0,
        "modificado": "",
        "et1": "",
        "lineaDeCredito": ""
    },
    "1500-0175": {
        "estado": "ACTIVO",
        "fecha": "2024-04-12",
        "nombre": "KAORI LISBET GARCIA ALVAREZ-MERCADITO CAMPESINO",
        "direccion": "C SIN NOMBRE MZA 10 LT9, COL LA PRESA 40893",
        "telefono1": "(755) 111-0234",
        "telefono2": "(___) ___-____",
        "descripcion": "",
        "email": "",
        "referencia": "PESCADORA-MORENA",
        "obs": "",
        "credito": true,
        "montoCredito": 5000.0,
        "diasCredito": 30,
        "interesCredito": "0",
        "saldo": 500.0,
        "nl": 0,
        "nc": "",
        "membresia": "2022-07-22",
        "nivel": 0,
        "modificado": "",
        "et1": "",
        "lineaDeCredito": "CLIENTE BASICO"
    },
    "1500-0179": {
        "estado": "ACTIVO",
        "fecha": "2024-09-24",
        "nombre": "ISMAEL MAGAÑA-MADERERIA",
        "direccion": "COL. AGUA DE CORREA POR LA FEDERAL DE CAMINO",
        "telefono1": "(755) 171-8946",
        "telefono2": "(___) ___-____",
        "descripcion": "",
        "email": "",
        "referencia": "",
        "obs": "",
        "credito": true,
        "montoCredito": 40000.0,
        "diasCredito": 30,
        "interesCredito": "1.00",
        "saldo": 7200.0,
        "nl": 0,
        "nc": "",
        "membresia": "2022-07-25",
        "nivel": 0,
        "modificado": "",
        "et1": "",
        "lineaDeCredito": ""
    },
    "1500-0185": {
        "estado": "ACTIVO",
        "fecha": "2024-10-10",
        "nombre": "JOSE LUIS FIGUEROA OREGON-TAXI 803 ANTES 02 VALLECITOS",
        "direccion": "C SIN NOMBRE SN LOC VALLECITOS GRO.",
        "telefono1": "(755) 100-3281",
        "telefono2": "(___) ___-____",
        "descripcion": "",
        "email": "",
        "referencia": "TAXI 802",
        "obs": "",
        "credito": true,
        "montoCredito": 2000.0,
        "diasCredito": 30,
        "interesCredito": "1.00",
        "saldo": 1100.0,
        "nl": 0,
        "nc": "",
        "membresia": "2022-07-27",
        "nivel": 0,
        "modificado": "",
        "et1": "",
        "lineaDeCredito": ""
    },
    "1500-0191": {
        "estado": "ACTIVO",
        "fecha": "2023-10-19",
        "nombre": "ISRAEL ALEJANDRO OTERO MARTINEZ",
        "direccion": "AND PEZ VOLADOR MZA 40 LT 6A, COL EMILIANO ZAPATA 40896",
        "telefono1": "(755) 113-6988",
        "telefono2": "(___) ___-____",
        "descripcion": "",
        "email": "",
        "referencia": "ISRAEL GOL ROJA",
        "obs": "",
        "credito": true,
        "montoCredito": 8000.0,
        "diasCredito": 30,
        "interesCredito": "1.00",
        "saldo": 3660.0,
        "nl": 0,
        "nc": "",
        "membresia": "2022-07-30",
        "nivel": 0,
        "modificado": "",
        "et1": "",
        "lineaDeCredito": ""
    },
    "1500-0193": {
        "estado": "ACTIVO",
        "fecha": "2024-09-04",
        "nombre": "VICENTA CALVARIO AHUIXTLE",
        "direccion": "C PISCIS MZA 12 LT 5, COL 12 DE MARZO 40894 , ZIHUATANEJO DE AZUETA",
        "telefono1": "(755) 131-2333",
        "telefono2": "(___) ___-____",
        "descripcion": "",
        "email": "",
        "referencia": "",
        "obs": "",
        "credito": true,
        "montoCredito": 10000.0,
        "diasCredito": 30,
        "interesCredito": "1.00",
        "saldo": 2000.0,
        "nl": 0,
        "nc": "",
        "membresia": "2022-08-01",
        "nivel": 0,
        "modificado": "",
        "et1": "",
        "lineaDeCredito": ""
    },
    "1500-0198": {
        "estado": "ACTIVO",
        "fecha": "2024-03-08",
        "nombre": "ALAN PEREZ CASTRO",
        "direccion": "",
        "telefono1": "(755) 120-3344",
        "telefono2": "(___) ___-____",
        "descripcion": "",
        "email": "",
        "referencia": "",
        "obs": "",
        "credito": true,
        "montoCredito": 7000.0,
        "diasCredito": 15,
        "interesCredito": "1.00",
        "saldo": 1925.0,
        "nl": 0,
        "nc": "",
        "membresia": "2022-08-03",
        "nivel": 0,
        "modificado": "",
        "et1": "",
        "lineaDeCredito": ""
    },
    "1500-0214": {
        "estado": "ACTIVO",
        "fecha": "2024-10-04",
        "nombre": "PRODEI-PROYECTOS Y DESARROLLO DE INGENIERIA",
        "direccion": "DOMICILIO CONOCIDO",
        "telefono1": "(755) 115-3313",
        "telefono2": "(___) ___-____",
        "descripcion": "",
        "email": "",
        "referencia": "",
        "obs": "",
        "credito": true,
        "montoCredito": 60000.0,
        "diasCredito": 30,
        "interesCredito": "1.00",
        "saldo": 200.0,
        "nl": 0,
        "nc": "",
        "membresia": "2022-08-12",
        "nivel": 0,
        "modificado": "",
        "et1": "",
        "lineaDeCredito": ""
    },
    "1500-0239": {
        "estado": "ACTIVO",
        "fecha": "2024-10-19",
        "nombre": "GUSTAVO RIOS ESPINO-TAXI 059-APAAZ",
        "direccion": "C. VICENTE GUERRERO #15 LOC SAN JERONIMITO CP 40831",
        "telefono1": "(755) 557-7129",
        "telefono2": "(___) ___-____",
        "descripcion": "",
        "email": "",
        "referencia": "TAXI APAAZ 059",
        "obs": "",
        "credito": true,
        "montoCredito": 5000.0,
        "diasCredito": 30,
        "interesCredito": "1.00",
        "saldo": 3400.0,
        "nl": 0,
        "nc": "",
        "membresia": "2022-08-23",
        "nivel": 0,
        "modificado": "",
        "et1": "",
        "lineaDeCredito": ""
    },
    "1500-0230": {
        "estado": "ACTIVO",
        "fecha": "2024-09-30",
        "nombre": "LUIS ALBERTO OREGON GARCIA",
        "direccion": "COL SAN JOSE IXTAPA S/N 40883 CALLE CDO",
        "telefono1": "(755) 108-5976",
        "telefono2": "(___) ___-____",
        "descripcion": "",
        "email": "",
        "referencia": "",
        "obs": "",
        "credito": true,
        "montoCredito": 12000.0,
        "diasCredito": 30,
        "interesCredito": "1.00",
        "saldo": 4200.0,
        "nl": 0,
        "nc": "",
        "membresia": "2022-08-18",
        "nivel": 0,
        "modificado": "",
        "et1": "",
        "lineaDeCredito": ""
    },
    "1500-0231": {
        "estado": "ACTIVO",
        "fecha": "2023-12-09",
        "nombre": "MIGUEL ANGEL ABARCA ROMERO",
        "direccion": "C AZTLAN S/N COL CUAHTEMOC 40896 ZIHUATANEJO DE AZUETA",
        "telefono1": "(755) 101-5007",
        "telefono2": "(___) ___-____",
        "descripcion": "",
        "email": "",
        "referencia": "TAXI 469 APAAZ",
        "obs": "",
        "credito": true,
        "montoCredito": 4000.0,
        "diasCredito": 30,
        "interesCredito": "1.00",
        "saldo": 1200.0,
        "nl": 0,
        "nc": "",
        "membresia": "2022-08-19",
        "nivel": 0,
        "modificado": "",
        "et1": "",
        "lineaDeCredito": ""
    },
    "1500-0253": {
        "estado": "ACTIVO",
        "fecha": "2024-10-30",
        "nombre": "PABLO RIVERA CADENA",
        "direccion": "AV. EL PALMAR S/N COL. PROGRESO",
        "telefono1": "(755) 121-1152",
        "telefono2": "(___) ___-____",
        "descripcion": "",
        "email": "",
        "referencia": "VENDEDOR DE MASA",
        "obs": "",
        "credito": true,
        "montoCredito": 5000.0,
        "diasCredito": 30,
        "interesCredito": "0",
        "saldo": 4000.0,
        "nl": 0,
        "nc": "",
        "membresia": "2022-09-04",
        "nivel": 0,
        "modificado": "",
        "et1": "",
        "lineaDeCredito": "CLIENTE BASICO"
    },
    "1500-0250": {
        "estado": "ACTIVO",
        "fecha": "2022-09-01",
        "nombre": "ARMANDO GUZMAN VARGAS",
        "direccion": "C BACO MZ 11 LT 13 COL EL EMBALSE CP 40894",
        "telefono1": "(755) 131-9237",
        "telefono2": "(___) ___-____",
        "descripcion": "",
        "email": "",
        "referencia": "",
        "obs": "",
        "credito": true,
        "montoCredito": 10000.0,
        "diasCredito": 30,
        "interesCredito": "1.00",
        "saldo": 1980.0,
        "nl": 0,
        "nc": "",
        "membresia": "2022-08-31",
        "nivel": 0,
        "modificado": "",
        "et1": "",
        "lineaDeCredito": ""
    },
    "1500-0274": {
        "estado": "ACTIVO",
        "fecha": "2023-07-19",
        "nombre": "ENRIQUE MILLAN HERNANDEZ-AMIGO APARICIO",
        "direccion": "FRACC MORROCOY CONDOMINIO 50 CASA L01 40880",
        "telefono1": "(755) 690-1880",
        "telefono2": "(___) ___-____",
        "descripcion": "",
        "email": "",
        "referencia": "CONOCIDO POR VICTOR PROTECCION CIVIL",
        "obs": "TEL. (755) 113-5368 TEL. (755) 132-6861",
        "credito": true,
        "montoCredito": 5000.0,
        "diasCredito": 30,
        "interesCredito": "1.00",
        "saldo": 4800.0,
        "nl": 0,
        "nc": "",
        "membresia": "2022-09-15",
        "nivel": 0,
        "modificado": "",
        "et1": "",
        "lineaDeCredito": ""
    },
    "1500-0297": {
        "estado": "ACTIVO",
        "fecha": "2024-09-30",
        "nombre": "MATERIALES SAN JERONIMO",
        "direccion": "CONOCIDO ZIHUATANEJO GRO",
        "telefono1": "(755) 121-9076",
        "telefono2": "(755) 554-2233",
        "descripcion": "",
        "email": "",
        "referencia": "",
        "obs": "TEL. (___) ___-____ TEL. (755) 121-9071 TEL. (755) 121-9071",
        "credito": true,
        "montoCredito": 30000.0,
        "diasCredito": 30,
        "interesCredito": "0",
        "saldo": 600.0,
        "nl": 0,
        "nc": "",
        "membresia": "2022-10-02",
        "nivel": 0,
        "modificado": "",
        "et1": "",
        "lineaDeCredito": "EMPRESA BASICA"
    },
    "1500-0312": {
        "estado": "ACTIVO",
        "fecha": "2024-10-23",
        "nombre": "COMISION FEDERAL DE ELECTRICIDAD",
        "direccion": "AVENIDA PASEO DE LA REFORMA 164 COL.CUAUHTEMOC",
        "telefono1": "(___) ___-____",
        "telefono2": "(___) ___-____",
        "descripcion": "",
        "email": "",
        "referencia": "CONTACTO; LIC LESLIE SANCHEZ CEL 777 264 0899",
        "obs": "",
        "credito": true,
        "montoCredito": 200000.0,
        "diasCredito": 30,
        "interesCredito": "1.00",
        "saldo": 54000.0,
        "nl": 0,
        "nc": "",
        "membresia": "2022-10-11",
        "nivel": 0,
        "modificado": "",
        "et1": "",
        "lineaDeCredito": ""
    },
    "1500-0659": {
        "estado": "ACTIVO",
        "fecha": "2024-10-23",
        "nombre": "OSCAR ILARIO CRUZ- TAXI 653",
        "direccion": "C. BATALLA DEL PALAMAR MZ. 28 LT 4  COL. MORELOS",
        "telefono1": "(757) 126-7778",
        "telefono2": "(_2_) ___-____",
        "descripcion": "",
        "email": "",
        "referencia": "TAXI 653",
        "obs": "TEL. (___) ___-____",
        "credito": true,
        "montoCredito": 5000.0,
        "diasCredito": 30,
        "interesCredito": "0",
        "saldo": 3200.0,
        "nl": 0,
        "nc": "",
        "membresia": "2024-07-31",
        "nivel": 0,
        "modificado": "",
        "et1": "",
        "lineaDeCredito": "CLIENTE BASICO"
    },
    "1500-0334": {
        "estado": "ACTIVO",
        "fecha": "2023-10-12",
        "nombre": "LUIS OSVALDO PEREZ BRAVO",
        "direccion": "C. BELLA VISTA MZA 6 LT5 COL. AMUZGOS",
        "telefono1": "(755) 140-9055",
        "telefono2": "(___) ___-____",
        "descripcion": "",
        "email": "",
        "referencia": "",
        "obs": "",
        "credito": true,
        "montoCredito": 10000.0,
        "diasCredito": 30,
        "interesCredito": "1.00",
        "saldo": 550.0,
        "nl": 0,
        "nc": "",
        "membresia": "2022-10-27",
        "nivel": 0,
        "modificado": "",
        "et1": "",
        "lineaDeCredito": ""
    },
    "1500-0177": {
        "estado": "ACTIVO",
        "fecha": "2024-10-31",
        "nombre": "FELIPE BELTRAN AYVAR - BURRO",
        "direccion": "COL LA ESPERANZA 40894, ZIHUATANEJO DE AZUETA , GRO",
        "telefono1": "(755) 113-3548",
        "telefono2": "(755) 130-7566",
        "descripcion": "",
        "email": "",
        "referencia": "RUTA BARRIL COMBI  08",
        "obs": "CORAL HIJA DE FELIPE TEL. 7551307566 TEL. (___) ___-____ TEL. (755) 121-2130",
        "credito": false,
        "montoCredito": 25000.0,
        "diasCredito": 30,
        "interesCredito": "0",
        "saldo": 11200.0,
        "nl": 0,
        "nc": "",
        "membresia": "2022-07-23",
        "nivel": 0,
        "modificado": "",
        "et1": "",
        "lineaDeCredito": "EMPRESAS ACTIVA"
    },
    "1500-0307": {
        "estado": "ACTIVO",
        "fecha": "2023-08-25",
        "nombre": "JOSE LUIS HERNANDEZ OSORIO",
        "direccion": "LOC EL CORRIENTOSO 40880 ZIHUATANEJO DE AZUETA",
        "telefono1": "(755) 134-4275",
        "telefono2": "(___) ___-____",
        "descripcion": "",
        "email": "",
        "referencia": "",
        "obs": "",
        "credito": true,
        "montoCredito": 15000.0,
        "diasCredito": 30,
        "interesCredito": "1.00",
        "saldo": 5000.0,
        "nl": 0,
        "nc": "",
        "membresia": "2022-10-07",
        "nivel": 0,
        "modificado": "",
        "et1": "",
        "lineaDeCredito": ""
    },
    "1500-0345": {
        "estado": "ACTIVO",
        "fecha": "2022-11-02",
        "nombre": "SINIESTRO H. AYUNTAMIENTO",
        "direccion": "",
        "telefono1": "(755) 111-0186",
        "telefono2": "(___) ___-____",
        "descripcion": "",
        "email": "",
        "referencia": "",
        "obs": "",
        "credito": true,
        "montoCredito": 5000.0,
        "diasCredito": 30,
        "interesCredito": "1.00",
        "saldo": 175.0,
        "nl": 0,
        "nc": "",
        "membresia": "2022-11-01",
        "nivel": 0,
        "modificado": "",
        "et1": "",
        "lineaDeCredito": ""
    },
    "1500-0347": {
        "estado": "ACTIVO",
        "fecha": "2024-10-30",
        "nombre": "IVAN GARCIA MURILLO-PANADERIA ARMIDA",
        "direccion": "C. AMADO NERVO 8A COL. VASO DE MIRAFLORES",
        "telefono1": "(755) 557-0469",
        "telefono2": "(___) ___-____",
        "descripcion": "",
        "email": "",
        "referencia": "",
        "obs": "",
        "credito": true,
        "montoCredito": 20000.0,
        "diasCredito": 30,
        "interesCredito": "1.00",
        "saldo": 1600.0,
        "nl": 0,
        "nc": "",
        "membresia": "2022-11-03",
        "nivel": 0,
        "modificado": "",
        "et1": "",
        "lineaDeCredito": ""
    },
    "1500-0379": {
        "estado": "ACTIVO",
        "fecha": "2024-11-01",
        "nombre": "MOFLES GARCIA",
        "direccion": "ZIHUATANEJO DE AZUETA",
        "telefono1": "(___) ___-____",
        "telefono2": "(___) ___-____",
        "descripcion": "",
        "email": "",
        "referencia": "PAPA DE MIGUEL",
        "obs": "",
        "credito": true,
        "montoCredito": 280000.0,
        "diasCredito": 30,
        "interesCredito": "1.00",
        "saldo": 49183.97,
        "nl": 0,
        "nc": "",
        "membresia": "2022-12-05",
        "nivel": 0,
        "modificado": "",
        "et1": "",
        "lineaDeCredito": ""
    },
    "1500-0234": {
        "estado": "ACTIVO",
        "fecha": "2024-10-08",
        "nombre": "JORGE ALBERTO SUAREZ NOGUEDA-180 RUTA CORREA",
        "direccion": "C. GRAL. JUAN N MENDEZ 195 COL. IGNACIO ZARAGOZA CP 58114",
        "telefono1": "(744) 383-9038",
        "telefono2": "(___) ___-____",
        "descripcion": "",
        "email": "",
        "referencia": "",
        "obs": "",
        "credito": true,
        "montoCredito": 5000.0,
        "diasCredito": 20,
        "interesCredito": "1.00",
        "saldo": 2900.0,
        "nl": 0,
        "nc": "",
        "membresia": "2022-08-21",
        "nivel": 0,
        "modificado": "",
        "et1": "",
        "lineaDeCredito": ""
    },
    "1500-0313": {
        "estado": "ACTIVO",
        "fecha": "2024-10-31",
        "nombre": "ENRIQUE BASABE ODRIOZOLA",
        "direccion": "EDIFICIO 82 DEPTO 302 U HAB INFONAVIT EL HUJAL",
        "telefono1": "(755) 111-7792",
        "telefono2": "(___) ___-____",
        "descripcion": "",
        "email": "",
        "referencia": "",
        "obs": "",
        "credito": true,
        "montoCredito": 20000.0,
        "diasCredito": 30,
        "interesCredito": "1.00",
        "saldo": 12800.0,
        "nl": 0,
        "nc": "",
        "membresia": "2022-10-11",
        "nivel": 0,
        "modificado": "",
        "et1": "",
        "lineaDeCredito": ""
    },
    "1500-0374": {
        "estado": "ACTIVO",
        "fecha": "2024-09-23",
        "nombre": "ANTONIO ROMERO LOPEZ-FRUTERIA FENIX",
        "direccion": "COL. CENTRO FRENTE A SALINAS Y ROCHA",
        "telefono1": "(755) 108-5175",
        "telefono2": "(755) 144-9438",
        "descripcion": "",
        "email": "",
        "referencia": "",
        "obs": "TEL. (___) ___-____ TEL. (___) ___-____",
        "credito": true,
        "montoCredito": 16500.0,
        "diasCredito": 30,
        "interesCredito": "1.00",
        "saldo": 9010.0,
        "nl": 0,
        "nc": "",
        "membresia": "2022-11-28",
        "nivel": 0,
        "modificado": "",
        "et1": "",
        "lineaDeCredito": ""
    },
    "1500-0391": {
        "estado": "ACTIVO",
        "fecha": "2024-10-08",
        "nombre": "JULIAN ALEJANDRO RESENDIZ FLORES-RUBEN CASTRO",
        "direccion": "C. COSTA MAR MZA 5 LT3 COL. VICENTE G",
        "telefono1": "(755) 102-9741",
        "telefono2": "(___) ___-____",
        "descripcion": "",
        "email": "",
        "referencia": "TAXI 506",
        "obs": "TEL. (755) 124-4490",
        "credito": true,
        "montoCredito": 10000.0,
        "diasCredito": 30,
        "interesCredito": "0",
        "saldo": 3800.0,
        "nl": 0,
        "nc": "",
        "membresia": "2022-12-18",
        "nivel": 0,
        "modificado": "",
        "et1": "",
        "lineaDeCredito": "CLIENTE FRECUE"
    },
    "1500-0408": {
        "estado": "ACTIVO",
        "fecha": "2024-10-23",
        "nombre": "ALEJANDRO GUIDO TORRES-LAVANDERIA",
        "direccion": "",
        "telefono1": "(755) 120-2601",
        "telefono2": "(___) ___-____",
        "descripcion": "",
        "email": "",
        "referencia": "",
        "obs": "",
        "credito": true,
        "montoCredito": 10000.0,
        "diasCredito": 20,
        "interesCredito": "1.00",
        "saldo": 6800.0,
        "nl": 0,
        "nc": "",
        "membresia": "2023-01-04",
        "nivel": 0,
        "modificado": "",
        "et1": "",
        "lineaDeCredito": ""
    },
    "1500-0418": {
        "estado": "ACTIVO",
        "fecha": "2023-01-11",
        "nombre": "FELIPE IGLESIAS PAJARITO",
        "direccion": "C. HELECHO MZA 30 LT 5, COLONIA IGNACIO MANUEL ALTAMIRANO 40896",
        "telefono1": "(755) 140-2203",
        "telefono2": "(___) ___-____",
        "descripcion": "",
        "email": "",
        "referencia": "PARAJITO",
        "obs": "CONOCIDO DE MIGUEL",
        "credito": true,
        "montoCredito": 3000.0,
        "diasCredito": 30,
        "interesCredito": "0",
        "saldo": 2800.0,
        "nl": 0,
        "nc": "",
        "membresia": "2023-01-10",
        "nivel": 0,
        "modificado": "",
        "et1": "",
        "lineaDeCredito": "CLIENTE NUEVO"
    },
    "1500-0233": {
        "estado": "ACTIVO",
        "fecha": "2024-10-19",
        "nombre": "FELIPE VICTORIANO RAMOS-TECNICO COCA",
        "direccion": "C SANTA FLOR MZA 10 LT4 COL. AMUZGOS",
        "telefono1": "(755) 111-1311",
        "telefono2": "(___) ___-____",
        "descripcion": "",
        "email": "",
        "referencia": "",
        "obs": "",
        "credito": true,
        "montoCredito": 10000.0,
        "diasCredito": 30,
        "interesCredito": "1.00",
        "saldo": 6000.0,
        "nl": 0,
        "nc": "",
        "membresia": "2022-08-19",
        "nivel": 0,
        "modificado": "",
        "et1": "",
        "lineaDeCredito": ""
    },
    "1500-0280": {
        "estado": "ACTIVO",
        "fecha": "2024-06-21",
        "nombre": "SILVESTRE LORENZO CABRERA",
        "direccion": "C. AXAYACATL MZ 12 LT 70 COL. CUAUHTEMOC",
        "telefono1": "(755) 108-2792",
        "telefono2": "(___) ___-____",
        "descripcion": "",
        "email": "",
        "referencia": "",
        "obs": "TEL. (755) 108-2792 TEL. (755) 140-1392",
        "credito": true,
        "montoCredito": 8000.0,
        "diasCredito": 30,
        "interesCredito": "0",
        "saldo": 500.0,
        "nl": 0,
        "nc": "",
        "membresia": "2022-09-20",
        "nivel": 0,
        "modificado": "",
        "et1": "",
        "lineaDeCredito": "CLIENTE ACTIVO"
    },
    "1500-0367": {
        "estado": "ACTIVO",
        "fecha": "2024-09-28",
        "nombre": "LUIS FERNANDO MIRANDA DE LOS SANTOS",
        "direccion": "CARR SAN MIGUELITO FRACC AYOCUAN MZA 7 LT19",
        "telefono1": "(755) 172-2039",
        "telefono2": "(___) ___-____",
        "descripcion": "",
        "email": "",
        "referencia": "",
        "obs": "",
        "credito": true,
        "montoCredito": 3000.0,
        "diasCredito": 30,
        "interesCredito": "1.00",
        "saldo": 2400.0,
        "nl": 0,
        "nc": "",
        "membresia": "2022-11-17",
        "nivel": 0,
        "modificado": "",
        "et1": "",
        "lineaDeCredito": ""
    },
    "1500-0410": {
        "estado": "ACTIVO",
        "fecha": "2024-10-30",
        "nombre": "JAVIER SANCHEZ OROZCO-AMIGO DE YOVANI",
        "direccion": "CALLE COCOS MZA 5 LOTE 19 COL. CENTRO",
        "telefono1": "(755) 101-8419",
        "telefono2": "(___) ___-____",
        "descripcion": "",
        "email": "",
        "referencia": "TAXI 716",
        "obs": "",
        "credito": true,
        "montoCredito": 5000.0,
        "diasCredito": 30,
        "interesCredito": "1.00",
        "saldo": 3830.0,
        "nl": 0,
        "nc": "",
        "membresia": "2023-01-05",
        "nivel": 0,
        "modificado": "",
        "et1": "",
        "lineaDeCredito": ""
    },
    "1500-0316": {
        "estado": "ACTIVO",
        "fecha": "2024-08-02",
        "nombre": "CRISPIN GARCIA ONOFRE",
        "direccion": "C 11 MZ 3 LT 3 COL 20 DE NOVIEMBRE 40893 ZIHUATANEJO DE AZUETA",
        "telefono1": "(755) 140-6072",
        "telefono2": "(___) ___-____",
        "descripcion": "",
        "email": "",
        "referencia": "MITSUBICHI CAMIONETA ROJA",
        "obs": "",
        "credito": true,
        "montoCredito": 5000.0,
        "diasCredito": 30,
        "interesCredito": "1.00",
        "saldo": 2650.0,
        "nl": 0,
        "nc": "",
        "membresia": "2022-10-13",
        "nivel": 0,
        "modificado": "",
        "et1": "",
        "lineaDeCredito": ""
    },
    "1500-0447": {
        "estado": "ACTIVO",
        "fecha": "2024-10-16",
        "nombre": "ZZO CONSTRUCCIONES S.A DE C.V.",
        "direccion": "CALLE PALMITO NO.EXT. MZA 4 NO. INT LT CP-1 40880, COLONIA LA PUERTA ZIHUATANEJO",
        "telefono1": "(755) 127-4505",
        "telefono2": "(___) ___-____",
        "descripcion": "",
        "email": "",
        "referencia": "",
        "obs": "",
        "credito": true,
        "montoCredito": 25000.0,
        "diasCredito": 30,
        "interesCredito": "1.00",
        "saldo": 1900.0,
        "nl": 0,
        "nc": "",
        "membresia": "2023-02-05",
        "nivel": 0,
        "modificado": "",
        "et1": "",
        "lineaDeCredito": ""
    },
    "1500-0471": {
        "estado": "ACTIVO",
        "fecha": "2024-06-25",
        "nombre": "FIBAZI",
        "direccion": "AV. JOSE MARIA MORELOS S/N COL. CENTRO",
        "telefono1": "(___) ___-____",
        "telefono2": "(___) ___-____",
        "descripcion": "",
        "email": "",
        "referencia": "",
        "obs": "",
        "credito": true,
        "montoCredito": 10000.0,
        "diasCredito": 30,
        "interesCredito": "1.00",
        "saldo": 300.0,
        "nl": 0,
        "nc": "",
        "membresia": "2023-03-05",
        "nivel": 0,
        "modificado": "",
        "et1": "",
        "lineaDeCredito": ""
    },
    "1500-0343": {
        "estado": "ACTIVO",
        "fecha": "2024-09-24",
        "nombre": "FRANCISCO JESUS CRUZ SANCHEZ-CACHORRO",
        "direccion": "AND JADE EDIF 52 DEPTO 302 INFONAVIT EL HUJAL",
        "telefono1": "(755) 121-6603",
        "telefono2": "(___) ___-____",
        "descripcion": "",
        "email": "",
        "referencia": "",
        "obs": "",
        "credito": true,
        "montoCredito": 10000.0,
        "diasCredito": 30,
        "interesCredito": "0",
        "saldo": 700.0,
        "nl": 0,
        "nc": "",
        "membresia": "2022-10-31",
        "nivel": 0,
        "modificado": "",
        "et1": "",
        "lineaDeCredito": "CLIENTE FRECUE"
    },
    "1500-0437": {
        "estado": "ACTIVO",
        "fecha": "2024-10-12",
        "nombre": "JAIRO",
        "direccion": "DOMICILIO CONOCIDO",
        "telefono1": "(755) 104-3721",
        "telefono2": "(___) ___-____",
        "descripcion": "",
        "email": "",
        "referencia": "",
        "obs": "",
        "credito": true,
        "montoCredito": 20000.0,
        "diasCredito": 30,
        "interesCredito": "0",
        "saldo": 5200.0,
        "nl": 0,
        "nc": "",
        "membresia": "2023-01-29",
        "nivel": 0,
        "modificado": "",
        "et1": "",
        "lineaDeCredito": "EMPRESA NUEVA"
    },
    "1500-0485": {
        "estado": "ACTIVO",
        "fecha": "2024-09-27",
        "nombre": "ARIEL GARCIA MURILLO-PANADERIA ARIEL",
        "direccion": "C.SIN NOMBRE MZA 20 LT 13 AMPL LOMAS DEL RISCAL",
        "telefono1": "(755) 557-7663",
        "telefono2": "(351) 518-8612",
        "descripcion": "",
        "email": "",
        "referencia": "CONTACTO; JOSE FREDY GARCIA",
        "obs": "",
        "credito": true,
        "montoCredito": 50000.0,
        "diasCredito": 30,
        "interesCredito": "1.00",
        "saldo": 2021.0,
        "nl": 0,
        "nc": "",
        "membresia": "2023-03-29",
        "nivel": 0,
        "modificado": "",
        "et1": "",
        "lineaDeCredito": ""
    },
    "1500-0486": {
        "estado": "ACTIVO",
        "fecha": "2024-10-07",
        "nombre": "JOSE ARROYO MAYO",
        "direccion": "C. CORRIENTE MAZ.3 LT2 COL EL EMBALSE",
        "telefono1": "(755) 102-0894",
        "telefono2": "(___) ___-____",
        "descripcion": "",
        "email": "",
        "referencia": "TAXI 611",
        "obs": "",
        "credito": true,
        "montoCredito": 5000.0,
        "diasCredito": 30,
        "interesCredito": "1.00",
        "saldo": 1100.0,
        "nl": 0,
        "nc": "",
        "membresia": "2023-04-03",
        "nivel": 0,
        "modificado": "",
        "et1": "",
        "lineaDeCredito": ""
    },
    "1500-0371": {
        "estado": "ACTIVO",
        "fecha": "2024-10-25",
        "nombre": "GAS MENGUC-GASERA GLOBAL GAS",
        "direccion": "CARR NAL ACAPULCO ZIHUATANEJO KM.235+600",
        "telefono1": "(755) 554-8400",
        "telefono2": "(___) ___-____",
        "descripcion": "",
        "email": "",
        "referencia": "",
        "obs": "",
        "credito": true,
        "montoCredito": 50000.0,
        "diasCredito": 30,
        "interesCredito": "0",
        "saldo": 1150.0,
        "nl": 0,
        "nc": "",
        "membresia": "2022-11-24",
        "nivel": 0,
        "modificado": "",
        "et1": "",
        "lineaDeCredito": "EMPRESA FRECUE"
    },
    "1500-0538": {
        "estado": "ACTIVO",
        "fecha": "2024-10-04",
        "nombre": "SERGIO ANTONIO GARCIA MARQUE- JESUS PURIFICADORA",
        "direccion": "LOC. LA MAJAHUA S/N 40804",
        "telefono1": "(755) 133-9603",
        "telefono2": "(___) ___-____",
        "descripcion": "",
        "email": "",
        "referencia": "AMIGO DE JESUS PURIFICADORA",
        "obs": "AMIGO DE JESUS PURIFICADORA",
        "credito": true,
        "montoCredito": 40000.0,
        "diasCredito": 30,
        "interesCredito": "1.00",
        "saldo": 2010.0,
        "nl": 0,
        "nc": "",
        "membresia": "2023-06-27",
        "nivel": 0,
        "modificado": "",
        "et1": "",
        "lineaDeCredito": ""
    },
    "1500-0540": {
        "estado": "ACTIVO",
        "fecha": "2024-07-04",
        "nombre": "RAUL MAGANDA GUTIERREZ",
        "direccion": "C. JUAN PINEDA MZA 60 LT1 COL. AGUA DE CORREA",
        "telefono1": "(755) 113-5655",
        "telefono2": "(___) ___-____",
        "descripcion": "",
        "email": "",
        "referencia": "TAXI 294 F.A.R.",
        "obs": "",
        "credito": true,
        "montoCredito": 5000.0,
        "diasCredito": 30,
        "interesCredito": "0",
        "saldo": 3300.0,
        "nl": 0,
        "nc": "",
        "membresia": "2023-06-27",
        "nivel": 0,
        "modificado": "",
        "et1": "",
        "lineaDeCredito": "CLIENTE BASICO"
    },
    "1500-0555": {
        "estado": "ACTIVO",
        "fecha": "2024-10-26",
        "nombre": "ALAMO-CLICK MOBILITY",
        "direccion": "INTERIOR AEROPUERTO",
        "telefono1": "(332) 450-7131",
        "telefono2": "(744) 208-9631",
        "descripcion": "",
        "email": "",
        "referencia": "FERNANDO SANTIAGO CONTACTO",
        "obs": "TEL. (___) ___-____ TEL. (___) ___-____",
        "credito": true,
        "montoCredito": 50000.0,
        "diasCredito": 30,
        "interesCredito": "0",
        "saldo": 3400.0,
        "nl": 0,
        "nc": "",
        "membresia": "2023-07-30",
        "nivel": 0,
        "modificado": "",
        "et1": "",
        "lineaDeCredito": "EMPRESA FRECUE"
    },
    "1500-0559": {
        "estado": "ACTIVO",
        "fecha": "2024-10-25",
        "nombre": "GALLINA-MECANICO FLORIBERTO SANTANA",
        "direccion": "DOM. CONOCIDO S/N",
        "telefono1": "(755) 558-0415",
        "telefono2": "(___) ___-____",
        "descripcion": "",
        "email": "",
        "referencia": "",
        "obs": "TEL. (___) ___-____",
        "credito": true,
        "montoCredito": 3000.0,
        "diasCredito": 30,
        "interesCredito": "0",
        "saldo": 650.0,
        "nl": 0,
        "nc": "",
        "membresia": "2023-08-06",
        "nivel": 0,
        "modificado": "",
        "et1": "",
        "lineaDeCredito": "CLIENTE NUEVO"
    },
    "1500-0569": {
        "estado": "ACTIVO",
        "fecha": "2024-10-29",
        "nombre": "JOSE LUIS FLORES MEJIA-PAQ. SERVICIOS ALTERNATIVOS",
        "direccion": "C. LAURELES S/N COL LA PAROTA DE LLANO LARGO",
        "telefono1": "(744) 211-2240",
        "telefono2": "(755) 113-2327",
        "descripcion": "",
        "email": "",
        "referencia": "",
        "obs": "TEL. (___) ___-____",
        "credito": true,
        "montoCredito": 8000.0,
        "diasCredito": 30,
        "interesCredito": "0",
        "saldo": 7100.0,
        "nl": 0,
        "nc": "",
        "membresia": "2023-08-30",
        "nivel": 0,
        "modificado": "",
        "et1": "",
        "lineaDeCredito": "CLIENTE ACTIVO"
    },
    "1500-0577": {
        "estado": "ACTIVO",
        "fecha": "2024-10-08",
        "nombre": "ESTEBAN PALOMINO GUTIERREZ-RUBEN TAXISTA",
        "direccion": "AV. LA LAJA MZA 6 LT 1 COL. VICENTE GUERRERO",
        "telefono1": "(755) 556-0042",
        "telefono2": "(755) 128-3372",
        "descripcion": "",
        "email": "",
        "referencia": "TAXI N.581",
        "obs": "",
        "credito": true,
        "montoCredito": 5000.0,
        "diasCredito": 30,
        "interesCredito": "1.00",
        "saldo": 4400.0,
        "nl": 0,
        "nc": "",
        "membresia": "2023-09-17",
        "nivel": 0,
        "modificado": "",
        "et1": "",
        "lineaDeCredito": ""
    },
    "1500-0585": {
        "estado": "ACTIVO",
        "fecha": "2024-04-01",
        "nombre": "JUAN ANTONIO ANAYA VALENCIA",
        "direccion": "CARR NAL ZIHUATANEJO LOC LA PUERTA DEL SOL",
        "telefono1": "(755) 127-1169",
        "telefono2": "(755) 113-4054",
        "descripcion": "",
        "email": "",
        "referencia": "SERVICIOS PUBLICOS",
        "obs": "",
        "credito": true,
        "montoCredito": 25000.0,
        "diasCredito": 30,
        "interesCredito": "0",
        "saldo": 600.0,
        "nl": 0,
        "nc": "",
        "membresia": "2023-10-06",
        "nivel": 0,
        "modificado": "",
        "et1": "",
        "lineaDeCredito": "EMPRESAS ACTIVA"
    },
    "1500-0587": {
        "estado": "ACTIVO",
        "fecha": "2024-07-01",
        "nombre": "CELEDONIO TEPEC TECONCO-TAXI 0390",
        "direccion": "CALLE LIRIOS COL. EL PARAISO",
        "telefono1": "(755) 143-9059",
        "telefono2": "(___) ___-____",
        "descripcion": "",
        "email": "",
        "referencia": "TAXI 0390",
        "obs": "",
        "credito": true,
        "montoCredito": 4500.0,
        "diasCredito": 30,
        "interesCredito": "1.00",
        "saldo": 1500.0,
        "nl": 0,
        "nc": "",
        "membresia": "2023-10-13",
        "nivel": 0,
        "modificado": "",
        "et1": "",
        "lineaDeCredito": ""
    },
    "1500-0588": {
        "estado": "ACTIVO",
        "fecha": "2024-10-14",
        "nombre": "GABINO JAVIER GARDUZA PINEDA-TAXI 704 UTAAZ",
        "direccion": "C. AGUA AZUL HAB. LA PUERTA 111",
        "telefono1": "(744) 552-7683",
        "telefono2": "(___) ___-____",
        "descripcion": "",
        "email": "",
        "referencia": "TAXI 704",
        "obs": "TEL. (755) 138-8658",
        "credito": true,
        "montoCredito": 5000.0,
        "diasCredito": 30,
        "interesCredito": "0",
        "saldo": 4400.0,
        "nl": 0,
        "nc": "",
        "membresia": "2023-10-16",
        "nivel": 0,
        "modificado": "",
        "et1": "",
        "lineaDeCredito": "CLIENTE BASICO"
    },
    "1500-0592": {
        "estado": "ACTIVO",
        "fecha": "2023-10-23",
        "nombre": "EDWIN CRUZ ARELLANES",
        "direccion": "AV. SIERVO DE LA NACION S/N COL. MORELOS",
        "telefono1": "(755) 130-3000",
        "telefono2": "(___) ___-____",
        "descripcion": "",
        "email": "",
        "referencia": "",
        "obs": "",
        "credito": true,
        "montoCredito": 10000.0,
        "diasCredito": 30,
        "interesCredito": "1.00",
        "saldo": 1500.0,
        "nl": 0,
        "nc": "",
        "membresia": "2023-10-22",
        "nivel": 0,
        "modificado": "",
        "et1": "",
        "lineaDeCredito": ""
    },
    "1500-0593": {
        "estado": "ACTIVO",
        "fecha": "2024-07-23",
        "nombre": "ROBERTO SOTELO HERNANDEZ-VALE APAAZ",
        "direccion": "C. SOR JUANA INES DE LA CRUZ 8 LOC. SAN JERONIMITO",
        "telefono1": "(755) 127-6366",
        "telefono2": "(___) ___-____",
        "descripcion": "",
        "email": "",
        "referencia": "TAXI 068",
        "obs": "",
        "credito": true,
        "montoCredito": 5000.0,
        "diasCredito": 30,
        "interesCredito": "1.00",
        "saldo": 900.0,
        "nl": 0,
        "nc": "",
        "membresia": "2023-10-25",
        "nivel": 0,
        "modificado": "",
        "et1": "",
        "lineaDeCredito": ""
    },
    "1500-0660": {
        "estado": "ACTIVO",
        "fecha": "2024-08-03",
        "nombre": "VICTOR MANUEL SERNA BERNAL",
        "direccion": "CO. AEROPUERTO 40880, ZIHUATANEJO DE AZUETA GRO.",
        "telefono1": "(755) 141-3520",
        "telefono2": "(___) ___-____",
        "descripcion": "",
        "email": "",
        "referencia": "",
        "obs": "",
        "credito": true,
        "montoCredito": 3000.0,
        "diasCredito": 30,
        "interesCredito": "0",
        "saldo": 750.0,
        "nl": 0,
        "nc": "",
        "membresia": "2024-08-02",
        "nivel": 0,
        "modificado": "",
        "et1": "",
        "lineaDeCredito": "CLIENTE NUEVO"
    },
    "1500-0610": {
        "estado": "ACTIVO",
        "fecha": "2024-07-29",
        "nombre": "LUIS ALBERTO FUERTE CORTEZ-KONAN",
        "direccion": "C. SIN NOMBRE MZA 5 LT 6 COL. EL CALECHOSO",
        "telefono1": "(755) 108-8045",
        "telefono2": "(___) ___-____",
        "descripcion": "",
        "email": "",
        "referencia": "",
        "obs": "",
        "credito": true,
        "montoCredito": 5000.0,
        "diasCredito": 30,
        "interesCredito": "0",
        "saldo": 4200.0,
        "nl": 0,
        "nc": "",
        "membresia": "2023-11-30",
        "nivel": 0,
        "modificado": "",
        "et1": "",
        "lineaDeCredito": "CLIENTE BASICO"
    },
    "1500-0290": {
        "estado": "ACTIVO",
        "fecha": "2024-10-23",
        "nombre": "ALEJANDRO MARTINEZ ALCOCER- TAXI 598",
        "direccion": "AV EDO DE MEXICO MZA 15 LT 3 COL MORELOS PARTE ALTA 40894",
        "telefono1": "(755) 100-8948",
        "telefono2": "(___) ___-____",
        "descripcion": "",
        "email": "",
        "referencia": "TAXI 555",
        "obs": "",
        "credito": true,
        "montoCredito": 5000.0,
        "diasCredito": 30,
        "interesCredito": "0",
        "saldo": 1900.0,
        "nl": 0,
        "nc": "",
        "membresia": "2022-09-26",
        "nivel": 0,
        "modificado": "",
        "et1": "",
        "lineaDeCredito": "CLIENTE BASICO"
    },
    "1500-0358": {
        "estado": "ACTIVO",
        "fecha": "2024-11-01",
        "nombre": "TRANSPORTE TURISTICO AEROPUERTO DE ZIHUATANEJO",
        "direccion": "BOULEVARD AEROPUERTO S/N",
        "telefono1": "(755) 553-7031",
        "telefono2": "(755) 133-2414",
        "descripcion": "",
        "email": "",
        "referencia": "SECRETARIA YESENIA 7551200923",
        "obs": "LIDER SR. ROBERTO MORA\r\nCEL 755 5565289",
        "credito": true,
        "montoCredito": 20000.0,
        "diasCredito": 30,
        "interesCredito": "0",
        "saldo": 7550.0,
        "nl": 0,
        "nc": "",
        "membresia": "2022-11-09",
        "nivel": 0,
        "modificado": "",
        "et1": "",
        "lineaDeCredito": "EMPRESA NUEVA"
    },
    "1500-0616": {
        "estado": "ACTIVO",
        "fecha": "2023-12-30",
        "nombre": "ADRIAN SANTIAGO ABARCA",
        "direccion": "C. SIN NOMBRE 54 COL. NUEVA CREACION DIAMANTE",
        "telefono1": "(755) 121-4757",
        "telefono2": "(755) 690-8414",
        "descripcion": "",
        "email": "",
        "referencia": "",
        "obs": "",
        "credito": true,
        "montoCredito": 10000.0,
        "diasCredito": 30,
        "interesCredito": "0",
        "saldo": 7280.0,
        "nl": 0,
        "nc": "",
        "membresia": "2023-12-18",
        "nivel": 0,
        "modificado": "",
        "et1": "",
        "lineaDeCredito": "CLIENTE FRECUE"
    },
    "1500-0495": {
        "estado": "ACTIVO",
        "fecha": "2024-10-31",
        "nombre": "GASOLINERA GONZALEZ-AUTOTRANSPORTES ZIHUATANEJO IXTAPA",
        "direccion": "C. CERRADA PALO DE ARCO COL. EL HUJAL",
        "telefono1": "(755) 114-7625",
        "telefono2": "(___) ___-____",
        "descripcion": "",
        "email": "",
        "referencia": "GASOLINERA GONZALEZ, CONTACTO; SRA. MINERVA MAGANDA CEL 7551147625",
        "obs": "TEL. (___) ___-____",
        "credito": true,
        "montoCredito": 25000.0,
        "diasCredito": 30,
        "interesCredito": "1.00",
        "saldo": 7200.0,
        "nl": 0,
        "nc": "",
        "membresia": "2023-04-11",
        "nivel": 0,
        "modificado": "",
        "et1": "",
        "lineaDeCredito": ""
    },
    "1500-0565": {
        "estado": "ACTIVO",
        "fecha": "2024-10-15",
        "nombre": "ROSALIO OLEA FUERTE -TAXI 138",
        "direccion": "C SIN NOMBRE MZA 12 LOTE 3 COL CALECHOSO CP 40894",
        "telefono1": "(755) 141-0926",
        "telefono2": "(___) ___-____",
        "descripcion": "",
        "email": "",
        "referencia": "",
        "obs": "",
        "credito": true,
        "montoCredito": 10000.0,
        "diasCredito": 30,
        "interesCredito": "1.00",
        "saldo": 3800.0,
        "nl": 0,
        "nc": "",
        "membresia": "2023-08-20",
        "nivel": 0,
        "modificado": "",
        "et1": "",
        "lineaDeCredito": ""
    },
    "1500-0633": {
        "estado": "ACTIVO",
        "fecha": "2024-03-01",
        "nombre": "DYANGO (PUBLICIDAD)",
        "direccion": "AV. MORELOS COL. VICENTE LOCAL. 2",
        "telefono1": "(755) 100-9475",
        "telefono2": "(___) ___-____",
        "descripcion": "",
        "email": "",
        "referencia": "",
        "obs": "TEL. (___) ___-____",
        "credito": true,
        "montoCredito": 5000.0,
        "diasCredito": 30,
        "interesCredito": "0",
        "saldo": 3200.0,
        "nl": 0,
        "nc": "",
        "membresia": "2024-02-29",
        "nivel": 0,
        "modificado": "",
        "et1": "",
        "lineaDeCredito": "CLIENTE BASICO"
    },
    "1500-0634": {
        "estado": "ACTIVO",
        "fecha": "2024-10-26",
        "nombre": "SERGIO CEDEÑO CORONA-URBAN 23 JOYAS-APAAZ",
        "direccion": "DOMICLIO CONOCIDO S/N",
        "telefono1": "(755) 102-6498",
        "telefono2": "(755) 124-2883",
        "descripcion": "",
        "email": "",
        "referencia": "",
        "obs": "",
        "credito": true,
        "montoCredito": 5000.0,
        "diasCredito": 30,
        "interesCredito": "0",
        "saldo": 2800.0,
        "nl": 0,
        "nc": "",
        "membresia": "2024-02-29",
        "nivel": 0,
        "modificado": "",
        "et1": "",
        "lineaDeCredito": "CLIENTE BASICO"
    },
    "1500-0635": {
        "estado": "ACTIVO",
        "fecha": "2024-10-07",
        "nombre": "ABIMAEL SOLORIO FIGUEROA",
        "direccion": "LOC VALLECITOS DE ZARAGOZA",
        "telefono1": "(755) 111-0771",
        "telefono2": "(___) ___-____",
        "descripcion": "",
        "email": "",
        "referencia": "",
        "obs": "",
        "credito": true,
        "montoCredito": 30000.0,
        "diasCredito": 30,
        "interesCredito": "0",
        "saldo": 7000.0,
        "nl": 0,
        "nc": "",
        "membresia": "2024-03-07",
        "nivel": 0,
        "modificado": "",
        "et1": "",
        "lineaDeCredito": "EMPRESA BASICA"
    },
    "1500-0564": {
        "estado": "ACTIVO",
        "fecha": "2023-08-21",
        "nombre": "LUIS MARTIN CARRASCO VALDEZ",
        "direccion": "AND. LAGUNA DEL CARMEN MZA 30 LT 5 COL. VICENTE GUERRERO",
        "telefono1": "(755) 114-7174",
        "telefono2": "(___) ___-____",
        "descripcion": "",
        "email": "",
        "referencia": "",
        "obs": "",
        "credito": true,
        "montoCredito": 5000.0,
        "diasCredito": 30,
        "interesCredito": "1.00",
        "saldo": 1000.0,
        "nl": 0,
        "nc": "",
        "membresia": "2023-08-20",
        "nivel": 0,
        "modificado": "",
        "et1": "",
        "lineaDeCredito": ""
    },
    "1500-0650": {
        "estado": "ACTIVO",
        "fecha": "2024-07-08",
        "nombre": "ROSENDO RESENDIZ ESPINO - AMIGO DE ALAN",
        "direccion": "CARR VIEJA A LA UNION MZA9 LT5 COL VICENTE GUERRERO 40897",
        "telefono1": "(755) 136-5154",
        "telefono2": "(___) ___-____",
        "descripcion": "",
        "email": "",
        "referencia": "URBAN B. VIEJO 04",
        "obs": "",
        "credito": true,
        "montoCredito": 5000.0,
        "diasCredito": 30,
        "interesCredito": "0",
        "saldo": 3600.0,
        "nl": 0,
        "nc": "",
        "membresia": "2024-06-07",
        "nivel": 0,
        "modificado": "",
        "et1": "",
        "lineaDeCredito": "CLIENTE BASICO"
    },
    "1500-0667": {
        "estado": "ACTIVO",
        "fecha": "2024-10-19",
        "nombre": "FRANCISCO JAVIER HERNANDEZ BATALLA",
        "direccion": "AND. PELICANOS MZA. 9 LT 3 COL. LIBERTA C.P 40880",
        "telefono1": "(755) 124-7159",
        "telefono2": "(___) ___-____",
        "descripcion": "",
        "email": "",
        "referencia": "TALACHERO",
        "obs": "",
        "credito": true,
        "montoCredito": 10000.0,
        "diasCredito": 30,
        "interesCredito": "0",
        "saldo": 1125.0,
        "nl": 0,
        "nc": "",
        "membresia": "2024-09-08",
        "nivel": 0,
        "modificado": "",
        "et1": "",
        "lineaDeCredito": "CLIENTE FRECUE"
    },
    "1500-0668": {
        "estado": "ACTIVO",
        "fecha": "2024-09-09",
        "nombre": "LEONEL ALARCON GARCIA",
        "direccion": "C. SIN NOMBRE S/N COL. LOMAS DE SOTELO LOC. EL COACOYUL C.P.40882",
        "telefono1": "(664) 823-0322",
        "telefono2": "(___) ___-____",
        "descripcion": "",
        "email": "",
        "referencia": "TRABAJADOR DE LA REFACCIONARIA LA ORIENTAL",
        "obs": "",
        "credito": true,
        "montoCredito": 8000.0,
        "diasCredito": 30,
        "interesCredito": "0",
        "saldo": 750.0,
        "nl": 0,
        "nc": "",
        "membresia": "2024-09-08",
        "nivel": 0,
        "modificado": "",
        "et1": "",
        "lineaDeCredito": "CLIENTE ACTIVO"
    },
    "1500-0670": {
        "estado": "ACTIVO",
        "fecha": "2024-10-31",
        "nombre": "CEASSI",
        "direccion": "CONOCIDO",
        "telefono1": "(747) 221-2636",
        "telefono2": "(___) ___-____",
        "descripcion": "",
        "email": "",
        "referencia": "FONATUR",
        "obs": "",
        "credito": true,
        "montoCredito": 400000.0,
        "diasCredito": 30,
        "interesCredito": "0",
        "saldo": 107970.0,
        "nl": 0,
        "nc": "",
        "membresia": "2024-09-29",
        "nivel": 0,
        "modificado": "",
        "et1": "",
        "lineaDeCredito": "CLIENTE POTENCI"
    },
    "1500-0671": {
        "estado": "ACTIVO",
        "fecha": "2024-10-03",
        "nombre": "JUAN EVANGELISTA SALINAS FLORES",
        "direccion": "PLAYA 16 RDCIAL FRAGATAS C,P 40880",
        "telefono1": "(__7) 551-0166",
        "telefono2": "(755) 558-6109",
        "descripcion": "EL SEGUNDO NUMERO ES DE SU ESPOSA",
        "email": "",
        "referencia": "",
        "obs": "",
        "credito": true,
        "montoCredito": 5000.0,
        "diasCredito": 30,
        "interesCredito": "0",
        "saldo": 2850.0,
        "nl": 0,
        "nc": "",
        "membresia": "2024-10-02",
        "nivel": 0,
        "modificado": "",
        "et1": "",
        "lineaDeCredito": "CLIENTE BASICO"
    },
    "1500-0673": {
        "estado": "ACTIVO",
        "fecha": "2024-10-14",
        "nombre": "AMALIA RAMIREZ SANCHEZ (HERMANA DEL RAFAEL SANCHEZ)",
        "direccion": "AND. MABGOS MZA. 16LT 3 COL. EL EMBALSE C.P 40894",
        "telefono1": "(755) 132-9224",
        "telefono2": "(___) ___-____",
        "descripcion": "",
        "email": "",
        "referencia": "DUEÑA DE LA TIENDA DE ROPA FRENTE A LA PAPA LOCA",
        "obs": "",
        "credito": true,
        "montoCredito": 8000.0,
        "diasCredito": 30,
        "interesCredito": "0",
        "saldo": 2800.0,
        "nl": 0,
        "nc": "",
        "membresia": "2024-10-13",
        "nivel": 0,
        "modificado": "",
        "et1": "",
        "lineaDeCredito": "CLIENTE ACTIVO"
    },
    "1500-0674": {
        "estado": "ACTIVO",
        "fecha": "2024-10-29",
        "nombre": "EMMANUEL NORIEGA PUERTO TAXI 561",
        "direccion": "AV. TAMARINDO MZA. 10 LT 7 COL. AGUA DE CORREA C.P 40893",
        "telefono1": "(244) 110-4594",
        "telefono2": "(755) 140-7117",
        "descripcion": "EL SEGUNDO ES NUMERO DE SU ESPOSA",
        "email": "",
        "referencia": "",
        "obs": "",
        "credito": true,
        "montoCredito": 8000.0,
        "diasCredito": 30,
        "interesCredito": "0",
        "saldo": 4200.0,
        "nl": 0,
        "nc": "",
        "membresia": "2024-10-28",
        "nivel": 0,
        "modificado": "",
        "et1": "",
        "lineaDeCredito": "CLIENTE ACTIVO"
    },
    "1500-0675": {
        "estado": "ACTIVO",
        "fecha": "2024-10-30",
        "nombre": "ONIVER HERNANDEZ BATALLA",
        "direccion": "",
        "telefono1": "(___) ___-____",
        "telefono2": "(___) ___-____",
        "descripcion": "",
        "email": "",
        "referencia": "",
        "obs": "",
        "credito": true,
        "montoCredito": 5000.0,
        "diasCredito": 30,
        "interesCredito": "0",
        "saldo": 750.0,
        "nl": 0,
        "nc": "",
        "membresia": "2024-10-29",
        "nivel": 0,
        "modificado": "",
        "et1": "",
        "lineaDeCredito": "CLIENTE BASICO"
    },
    "1500-0676": {
        "estado": "ACTIVO",
        "fecha": "2024-11-01",
        "nombre": "ROGELIO LOPRZ SANCHEZ",
        "direccion": "INFONAVID EL HUJAL EDIF 111 DEP. 202 AVENIDA CIRCUITO AMATISTA",
        "telefono1": "(755) 120-5110",
        "telefono2": "(___) ___-____",
        "descripcion": "",
        "email": "",
        "referencia": "",
        "obs": "",
        "credito": true,
        "montoCredito": 5000.0,
        "diasCredito": 30,
        "interesCredito": "0",
        "saldo": 800.0,
        "nl": 0,
        "nc": "",
        "membresia": "2024-10-31",
        "nivel": 0,
        "modificado": "",
        "et1": "",
        "lineaDeCredito": "CLIENTE BASICO"
    },
    "1500-0558": {
        "estado": "ACTIVO",
        "fecha": "2024-10-21",
        "nombre": "JOSE ANGEL REYES ORNELAS",
        "direccion": "C. SIN NOMBRE MZA 32 LT1 COL. LOMAS DEL QUEBRACHAL",
        "telefono1": "(755) 558-2002",
        "telefono2": "(___) ___-____",
        "descripcion": "",
        "email": "",
        "referencia": "",
        "obs": "",
        "credito": true,
        "montoCredito": 12000.0,
        "diasCredito": 30,
        "interesCredito": "1.00",
        "saldo": 5800.0,
        "nl": 0,
        "nc": "",
        "membresia": "2023-08-02",
        "nivel": 0,
        "modificado": "",
        "et1": "",
        "lineaDeCredito": ""
    },
    "1500-0350": {
        "estado": "ACTIVO",
        "fecha": "2024-11-01",
        "nombre": "BENIGNO VARGAS CARMONA",
        "direccion": "C. MAGNOLIAS MZA 2 LT 1 COL. BENITO JUAREZ",
        "telefono1": "(755) 120-6054",
        "telefono2": "(___) ___-____",
        "descripcion": "",
        "email": "",
        "referencia": "",
        "obs": "",
        "credito": true,
        "montoCredito": 5000.0,
        "diasCredito": 30,
        "interesCredito": "1.00",
        "saldo": 1500.0,
        "nl": 0,
        "nc": "",
        "membresia": "2022-11-03",
        "nivel": 0,
        "modificado": "",
        "et1": "",
        "lineaDeCredito": ""
    },
    "1500-0308": {
        "estado": "ACTIVO",
        "fecha": "2024-11-01",
        "nombre": "XAVIER GALINDO MOLINA-MECANICO BARRIO VIEJO",
        "direccion": "BARRIO VIEJO",
        "telefono1": "(755) 138-8905",
        "telefono2": "(___) ___-____",
        "descripcion": "",
        "email": "",
        "referencia": "MECANICO DE BARRIO VIEJO",
        "obs": "",
        "credito": true,
        "montoCredito": 10000.0,
        "diasCredito": 15,
        "interesCredito": "1.00",
        "saldo": 4200.0,
        "nl": 0,
        "nc": "",
        "membresia": "2022-10-09",
        "nivel": 0,
        "modificado": "",
        "et1": "",
        "lineaDeCredito": ""
    },
    "1500-0594": {
        "estado": "ACTIVO",
        "fecha": "2024-11-02",
        "nombre": "ALFREDO VAZQUEZ LOPEZ-VALE UTAAZ",
        "direccion": "C. CHEPETEC MZA 8 LT 18 COL. PROGRESO",
        "telefono1": "(755) 104-6753",
        "telefono2": "(___) ___-____",
        "descripcion": "",
        "email": "",
        "referencia": "TAXI 599",
        "obs": "",
        "credito": true,
        "montoCredito": 5000.0,
        "diasCredito": 30,
        "interesCredito": "1.00",
        "saldo": 3300.0,
        "nl": 0,
        "nc": "",
        "membresia": "2023-10-25",
        "nivel": 0,
        "modificado": "",
        "et1": "",
        "lineaDeCredito": ""
    }
}